Metadata-Version: 1.1
Name: cogscik
Version: 1.0
Summary: Clustering Algorithm Motivated by Cognitive Science
Home-page: https://github.com/jamescwu/CogSciK
Author: James Wu & William Rivera
Author-email: jameswu2019@gmail.com
License: MIT
Download-URL: https://github.com/jamescwu/cogscik/archive/0.1.tar.gz
Keywords: clustering,decision-making,algorithm,cognitive science
Platform: UNKNOWN
Classifier: Development Status :: 5 - Production/Stable
Classifier: License :: OSI Approved :: MIT License
Classifier: Programming Language :: Python :: 2.7
